ticfile.py
ticfile-0.1.dist-info/LICENSE
ticfile-0.1.dist-info/METADATA
ticfile-0.1.dist-info/WHEEL
ticfile-0.1.dist-info/top_level.txt
ticfile-0.1.dist-info/zip-safe
ticfile-0.1.dist-info/RECORD
