Metadata-Version: 2.1
Name: ticfile
Version: 0.1
Summary: A library for reading and writing TIC-80 .tic cartridge files
Home-page: https://github.com/gasman/ticfile
Author: Matt Westcott
Author-email: matt@west.co.tt
License: BSD
Classifier: Development Status :: 3 - Alpha
Classifier: Intended Audience :: Developers
Classifier: License :: OSI Approved :: BSD License
Classifier: Operating System :: OS Independent
Classifier: Programming Language :: Python
Classifier: Programming Language :: Python :: 3
Classifier: Programming Language :: Python :: 3.7
Classifier: Programming Language :: Python :: 3.8
Classifier: Programming Language :: Python :: 3.9
Classifier: Programming Language :: Python :: 3.10
Classifier: Programming Language :: Python :: 3.11
Classifier: Topic :: System :: Emulators
Requires-Python: >=3.7
License-File: LICENSE
